lyon/__init__.py
lyon/calc.py
lyon/liblyon.so
lyon/utils.py
lyon-1.0.0.dist-info/LICENSE
lyon-1.0.0.dist-info/METADATA
lyon-1.0.0.dist-info/WHEEL
lyon-1.0.0.dist-info/top_level.txt
lyon-1.0.0.dist-info/RECORD
