Metadata-Version: 2.1
Name: lyon
Version: 1.0.0
Summary: Python port of Lyon's model from AuditoryToolbox
Home-page: https://github.com/sciforce/lyon
Maintainer: Dmytro Tkanov
Maintainer-email: dtkanov@sciforce.solutions
License: Apache License 2.0
Platform: UNKNOWN
Classifier: Programming Language :: Python :: 3
Classifier: License :: OSI Approved :: Apache Software License
Classifier: Operating System :: POSIX :: Linux
Classifier: Topic :: Multimedia :: Sound/Audio
Requires-Dist: numpy
